pyamasicp/__init__.py
pyamasicp/__main__.py
pyamasicp/client.py
pyamasicp/commands.py
pyamasicp-0.3.2.dist-info/METADATA
pyamasicp-0.3.2.dist-info/WHEEL
pyamasicp-0.3.2.dist-info/licenses/LICENSE
pyamasicp-0.3.2.dist-info/RECORD
