Metadata-Version: 2.4
Name: pyamasicp
Version: 0.3.2
Summary: Client for iiyama TV rs232 over lan protocol
Project-URL: Homepage, https://github.com/konikvranik/pyamasicp/
Project-URL: Issues, https://github.com/konikvranik/pyamasicp/issues
Author-email: Petr Vraník <hpa@suteren.net>
License-Expression: MIT
License-File: LICENSE
Keywords: SICP,TV,home-assistant,home-automation,iiyama,lan,monitor,rs232
Classifier: Development Status :: 4 - Beta
Classifier: License :: OSI Approved :: MIT License
Classifier: Programming Language :: Python :: 3
Classifier: Programming Language :: Python :: 3 :: Only
Classifier: Programming Language :: Python :: 3.10
Classifier: Programming Language :: Python :: 3.12
Classifier: Topic :: Home Automation
Classifier: Topic :: Multimedia
Classifier: Topic :: Utilities
Requires-Python: >=3.12
